hc128.py
pyHC128-1.0.2.dist-info/METADATA
pyHC128-1.0.2.dist-info/WHEEL
pyHC128-1.0.2.dist-info/top_level.txt
pyHC128-1.0.2.dist-info/RECORD
