Metadata-Version: 2.1
Name: pyHC128
Version: 1.0.2
Summary: pyHC128 is a Python package for the HC-128 stream cipher. It uses a 128-bit key and IV to generate a keystream.
Requires-Python: >=3.6
